art/__init__.py
art/auto_trajectory.py
art/backend.py
art/batches.py
art/cli.py
art/errors.py
art/gather.py
art/guided_completion.py
art/loss.py
art/model.py
art/openai.py
art/py.typed
art/trajectories.py
art/types.py
art/yield_trajectory.py
art/dev/__init__.py
art/dev/engine.py
art/dev/get_model_config.py
art/dev/model.py
art/dev/openai_server.py
art/dev/train.py
art/langgraph/__init__.py
art/langgraph/llm_wrapper.py
art/langgraph/logging.py
art/langgraph/message_utils.py
art/local/__init__.py
art/local/backend.py
art/local/checkpoints.py
art/local/service.py
art/mcp/__init__.py
art/mcp/default_tools.py
art/mcp/generate_scenarios.py
art/mcp/types.py
art/pipeline_trainer/__init__.py
art/pipeline_trainer/binary_prefix_tool_pipeline.py
art/pipeline_trainer/state.py
art/pipeline_trainer/status.py
art/pipeline_trainer/trainer.py
art/pipeline_trainer/types.py
art/pipeline_trainer/yes_no_maybe_pipeline.py
art/preprocessing/__init__.py
art/preprocessing/inputs.py
art/preprocessing/pack.py
art/preprocessing/tokenize.py
art/rewards/__init__.py
art/rewards/ruler.py
art/serverless/__init__.py
art/serverless/backend.py
art/serverless/client.py
art/test/test_step_skipping.py
art/tinker/__init__.py
art/tinker/backend.py
art/tinker/prefix_cache.py
art/tinker/renderers.py
art/tinker/server.py
art/tinker/service.py
art/tinker/cookbook_v/__init__.py
art/tinker/cookbook_v/hyperparam_utils.py
art/tinker/cookbook_v/image_processing_utils.py
art/tinker/cookbook_v/tokenizer_utils.py
art/tinker/cookbook_v/renderers/__init__.py
art/tinker/cookbook_v/renderers/base.py
art/tinker/cookbook_v/renderers/deepseek_v3.py
art/tinker/cookbook_v/renderers/gpt_oss.py
art/tinker/cookbook_v/renderers/kimi_k2.py
art/tinker/cookbook_v/renderers/llama3.py
art/tinker/cookbook_v/renderers/qwen3.py
art/tinker/cookbook_v/renderers/role_colon.py
art/tinker/cookbook_v/utils/__init__.py
art/tinker/cookbook_v/utils/misc_utils.py
art/tinker_native/__init__.py
art/tinker_native/backend.py
art/tinker_native/data.py
openpipe_art-0.5.9.dist-info/METADATA
openpipe_art-0.5.9.dist-info/WHEEL
openpipe_art-0.5.9.dist-info/entry_points.txt
openpipe_art-0.5.9.dist-info/licenses/LICENSE
openpipe_art-0.5.9.dist-info/RECORD
