Metadata-Version: 2.4
Name: openpipe-art
Version: 0.5.9
Summary: The OpenPipe Agent Reinforcement Training (ART) library
License-File: LICENSE
Requires-Python: >=3.11
Requires-Dist: litellm>=1.71.1
Requires-Dist: nest-asyncio>=1.6.0
Requires-Dist: openai>=2.14.0
Requires-Dist: polars>=1.26.0
Requires-Dist: setproctitle>=1.3.6
Requires-Dist: tblib>=3.0.0
Requires-Dist: typer>=0.15.2
Requires-Dist: weave>=0.52.23
Provides-Extra: backend
Requires-Dist: accelerate==1.7.0; extra == 'backend'
Requires-Dist: awscli>=1.38.1; extra == 'backend'
Requires-Dist: bitsandbytes>=0.45.2; extra == 'backend'
Requires-Dist: duckdb>=1.0.0; extra == 'backend'
Requires-Dist: gql<4; extra == 'backend'
Requires-Dist: hf-xet>=1.1.0; extra == 'backend'
Requires-Dist: nbclient>=0.10.1; extra == 'backend'
Requires-Dist: nbmake>=1.5.5; extra == 'backend'
Requires-Dist: peft>=0.14.0; extra == 'backend'
Requires-Dist: pyarrow>=15.0.0; extra == 'backend'
Requires-Dist: pytest>=8.4.1; extra == 'backend'
Requires-Dist: setuptools>=78.1.0; extra == 'backend'
Requires-Dist: torch>=2.8.0; extra == 'backend'
Requires-Dist: torchao==0.14.1; extra == 'backend'
Requires-Dist: transformers<=4.57.3,>=4.55.2; extra == 'backend'
Requires-Dist: trl==0.20.0; extra == 'backend'
Requires-Dist: unsloth-zoo==2025.12.7; extra == 'backend'
Requires-Dist: unsloth==2025.12.9; extra == 'backend'
Requires-Dist: vllm==0.13.0; extra == 'backend'
Requires-Dist: wandb==0.23.1; extra == 'backend'
Provides-Extra: langgraph
Requires-Dist: langchain-core>=0.3.51; extra == 'langgraph'
Requires-Dist: langchain-openai>=0.3.27; extra == 'langgraph'
Requires-Dist: langgraph>=0.6.2; extra == 'langgraph'
Provides-Extra: plotting
Requires-Dist: matplotlib>=3.10.1; extra == 'plotting'
Requires-Dist: seaborn>=0.13.2; extra == 'plotting'
Provides-Extra: tinker
Requires-Dist: datrie>=0.8.3; extra == 'tinker'
Requires-Dist: fastapi>=0.128.0; extra == 'tinker'
Requires-Dist: huggingface-hub; extra == 'tinker'
Requires-Dist: numpy; extra == 'tinker'
Requires-Dist: pillow; extra == 'tinker'
Requires-Dist: pydantic>=2.12.5; extra == 'tinker'
Requires-Dist: tinker>=0.8.1; extra == 'tinker'
Requires-Dist: torch>=2.8.0; extra == 'tinker'
Requires-Dist: transformers<=4.57.3,>=4.55.2; extra == 'tinker'
Requires-Dist: uvicorn>=0.35.0; extra == 'tinker'
